reflectdetect/PanelProperties.py
reflectdetect/__init__.py
reflectdetect/apriltag_main.py
reflectdetect/constants.py
reflectdetect/converter_main.py
reflectdetect/geolocation_main.py
reflectdetect/manufacturer/__init__.py
reflectdetect/manufacturer/generic/__init__.py
reflectdetect/manufacturer/generic/generic_utils.py
reflectdetect/manufacturer/micasense/__init__.py
reflectdetect/manufacturer/micasense/micasense_metadata.py
reflectdetect/manufacturer/micasense/micasense_utils.py
reflectdetect/pipeline.py
reflectdetect/utils/__init__.py
reflectdetect/utils/apriltags.py
reflectdetect/utils/debug.py
reflectdetect/utils/exif.py
reflectdetect/utils/iterators.py
reflectdetect/utils/orthophoto.py
reflectdetect/utils/panel.py
reflectdetect/utils/paths.py
reflectdetect/utils/polygons.py
reflectdetect/utils/tests/test_apriltags.py
reflectdetect/utils/tests/test_exif.py
reflectdetect/utils/tests/test_iterators.py
reflectdetect/utils/tests/test_orthophoto.py
reflectdetect/utils/thread.py
reflectdetect-1.0.2.dist-info/LICENSE
reflectdetect-1.0.2.dist-info/METADATA
reflectdetect-1.0.2.dist-info/WHEEL
reflectdetect-1.0.2.dist-info/entry_points.txt
reflectdetect-1.0.2.dist-info/RECORD
