Metadata-Version: 2.1
Name: reflectdetect
Version: 1.0.2
Summary: An automated workflow for in-flight radiometric calibration of UAV imagery
Home-page: https://github.com/reflectdetect/reflectdetect
License: GPL-3.0-or-later
Author: Luca Francis
Author-email: lucajoshua.francis@stud.uni-goettingen.de
Requires-Python: >=3.10,<4.0
Classifier: License :: OSI Approved :: GNU General Public License v3 or later (GPLv3+)
Classifier: Programming Language :: Python :: 3
Classifier: Programming Language :: Python :: 3.10
Classifier: Programming Language :: Python :: 3.11
Classifier: Programming Language :: Python :: 3.12
Requires-Dist: fiona (>=1,<2)
Requires-Dist: geopandas (>=1,<2)
Requires-Dist: matplotlib (>=3,<4)
Requires-Dist: numpy (>=2,<3)
Requires-Dist: opencv-python (>=4,<5)
Requires-Dist: pydantic (>=2,<3)
Requires-Dist: pyexiftool (>=0.5.6,<0.6.0)
Requires-Dist: rasterio (>=1,<2)
Requires-Dist: rich (>=13,<14)
Requires-Dist: rich-argparse (>=1,<2)
Requires-Dist: robotpy-apriltag (>=2025,<2026)
Requires-Dist: shapely (>=2,<3)
Requires-Dist: tifffile (>=2025,<2026)
Requires-Dist: tqdm (>=4,<5)
Requires-Dist: typed-argument-parser (>=1,<2)
Project-URL: Repository, https://github.com/reflectdetect/reflectdetect
